{
  "project_info": {
    "project_number": "206691766768",
    "firebase_url": "https://otaqtk-ba406.firebaseio.com",
    "project_id": "otaqtk-ba406",
    "storage_bucket": "otaqtk-ba406.appspot.com"
  },
  "client": [
    {
      "client_info": {
        "mobilesdk_app_id": "1:206691766768:android:a1c245a9c6ef2ddc66cd35",
        "android_client_info": {
          "package_name": "com.example.otaqtk"
        }
      },
      "oauth_client": [
        {
          "client_id": "206691766768-2tmm63v14v97ombh9tcphn2gmb62hr6q.apps.googleusercontent.com",
          "client_type": 1,
          "android_info": {
            "package_name": "com.example.otaqtk",
            "certificate_hash": "b7e23184c7c567bd3ee6aa73c87f1f32c98946ee"
          }
        },
        {
          "client_id": "206691766768-g78t5h3kiqde2ah843ibc7lsf7ffbslc.apps.googleusercontent.com",
          "client_type": 3
        }
      ],
      "api_key": [
        {
          "current_key": "AIzaSyCBNX2SD_brgjF9KaHlk9M7ST1iJByh_AE"
        }
      ],
      "services": {
        "appinvite_service": {
          "other_platform_oauth_client": [
            {
              "client_id": "206691766768-g78t5h3kiqde2ah843ibc7lsf7ffbslc.apps.googleusercontent.com",
              "client_type": 3
            },
            {
              "client_id": "206691766768-ao0e5o4r0a6fug9jsshqbpe3jnp2kts0.apps.googleusercontent.com",
              "client_type": 2,
              "ios_info": {
                "bundle_id": "com.Isitokari.Otaqtk"
              }
            }
          ]
        }
      }
    }
  ],
  "configuration_version": "1"
}